django_restful_admin/__init__.py
django_restful_admin/admin.py
django_restful_admin/apps.py
django_restful_admin_ppb-1.1.4.dist-info/LICENSE
django_restful_admin_ppb-1.1.4.dist-info/METADATA
django_restful_admin_ppb-1.1.4.dist-info/WHEEL
django_restful_admin_ppb-1.1.4.dist-info/top_level.txt
django_restful_admin_ppb-1.1.4.dist-info/RECORD
