Metadata-Version: 2.1
Name: django-restful-admin-ppb
Version: 1.1.4
Summary: Python Django RestFul Admin (forked by PPB)
Home-page: https://github.com/surface-security/django-restful-admin-ppb/
Author: PPB - InfoSec Engineering
Author-email: surface@paddypowerbetfair.com
License: MIT
Keywords: django restful admin
Platform: UNKNOWN
Classifier: Development Status :: 4 - Beta
Classifier: Intended Audience :: Developers
Classifier: Topic :: Software Development :: Build Tools
Classifier: License :: OSI Approved :: MIT License
Classifier: Programming Language :: Python :: 2
Classifier: Programming Language :: Python :: 2.7
Classifier: Programming Language :: Python :: 3
Classifier: Programming Language :: Python :: 3.3
Classifier: Programming Language :: Python :: 3.4
Classifier: Programming Language :: Python :: 3.5
License-File: LICENSE
Requires-Dist: django (>=2.0.0)
Requires-Dist: djangorestframework (>=3.0.0)
